LICENSE
MANIFEST.in
README.md
setup.cfg
setup.py
versioneer.py
aemcmc/__init__.py
aemcmc/_version.py
aemcmc/basic.py
aemcmc/conjugates.py
aemcmc/dists.py
aemcmc/ffbs.py
aemcmc/gibbs.py
aemcmc/nuts.py
aemcmc/rewriting.py
aemcmc/transforms.py
aemcmc/types.py
aemcmc/utils.py
aemcmc.egg-info/PKG-INFO
aemcmc.egg-info/SOURCES.txt
aemcmc.egg-info/dependency_links.txt
aemcmc.egg-info/not-zip-safe
aemcmc.egg-info/requires.txt
aemcmc.egg-info/top_level.txt