Metadata-Version: 2.1
Name: aemcmc
Version: 0.0.8
Summary: Miscellaneous MCMC samplers written in Aesara
Home-page: http://github.com/aesara-devs/aemcmc
Author: aesara-devs
Author-email: aesara.devs@gmail.com
License: UNKNOWN
Keywords: math,probability,numerical,symbolic,MCMC
Platform: UNKNOWN
Classifier: Development Status :: 4 - Beta
Classifier: Intended Audience :: Science/Research
Classifier: Intended Audience :: Developers
Classifier: License :: OSI Approved :: MIT License
Classifier: Operating System :: OS Independent
Classifier: Programming Language :: Python
Classifier: Programming Language :: Python :: 3
Classifier: Programming Language :: Python :: 3.8
Classifier: Programming Language :: Python :: 3.9
Classifier: Programming Language :: Python :: 3.10
Classifier: Programming Language :: Python :: Implementation :: CPython
Classifier: Programming Language :: Python :: Implementation :: PyPy
Requires-Python: >=3.8
